shabbir_library
