Metadata-Version: 1.0
Name: shabbir-library
Version: 0.11
Summary: operation & greeting library
Home-page: UNKNOWN
Author: UNKNOWN
Author-email: shabbirg89@gmail.com
License: UNKNOWN
Platform: UNKNOWN
